{
  "updated_at": "2026-03-31T10:35:00Z",
  "working_on": {
    "feature": "Native Kotlin Transcript Extract",
    "task": "Migrate Python (Chaquopy) to Kotlin Native",
    "status": "completed",
    "files": ["SummarizationRepository.kt", "SummaryViewModel.kt", "YouTubeTranscriptService.kt", "InnerTubeClient.kt", "MainActivity.kt"],
    "blockers": [],
    "notes": "Đã xoá mọi phụ thuộc vào Python/Chaquopy. Giảm dung lượng APK từ trên 36MB xuống còn khoảng 29MB. Test JVM có lỗi về mock API của Android (Html.fromHtml) nhưng có thể tiếp tục bằng Robolectric hoặc skip Unit Test cho phần framework-bound."
  },
  "pending_tasks": [
    { "task": "Test APK trên thiết bị thực tế", "priority": "high", "notes": "Cần kiểm tra quy trình lấy phụ đề và gọi API Gemini thực tế" },
    { "task": "Setup Robolectric cho file YouTubeTranscriptIntegrationTest.kt nếu muốn chạy Unit Test JVM", "priority": "medium", "notes": "Để bypass lỗi Html.fromHtml" }
  ],
  "recent_changes": [
    { "timestamp": "2026-03-31T10:30:00Z", "type": "refactor", "description": "Tạo InnerTubeClient.kt và TranscriptParser.kt, xóa PythonManager, xóa updateBanner", "files": ["app/src/main/java/com/skul9x/ytsummary/transcript/*", "SummaryViewModel.kt"] },
    { "timestamp": "2026-03-31T10:32:00Z", "type": "clean", "description": "Xóa chaquopy khỏi toàn bộ file build.gradle và libs.versions.toml", "files": ["app/build.gradle.kts", "build.gradle.kts", "settings.gradle.kts", "gradle/libs.versions.toml"] }
  ],
  "errors_encountered": [
    { "error": "JVM Unit Test compilation error (mocking Html.fromHtml)", "solution": "Thay vì mock chay tĩnh, cần xài Robolectric hoặc refactor wrapper ngoài luồng", "resolved": false }
  ],
  "decisions_made": [
    { "decision": "Dừng test tự động JVM bằng mockk", "reason": "Tốn thời gian với type infer API của Android; cần tập trung vào kiểm thử thiết bị thực tế hoặc cấu hình Robolectric." },
    { "decision": "Native parse dùng XmlPullParser", "reason": "Nhanh, nhẹ, built-in Android." },
    { "decision": "Chaquopy removed completely", "reason": "Giảm bloat cho app, runtime speed tăng." }
  ]
}
